simplemachinesforum/__init__.py
simplemachinesforum/simplemachinesforum.py
simplemachinesforum-0.4.5.dist-info/LICENSE
simplemachinesforum-0.4.5.dist-info/METADATA
simplemachinesforum-0.4.5.dist-info/WHEEL
simplemachinesforum-0.4.5.dist-info/top_level.txt
simplemachinesforum-0.4.5.dist-info/RECORD
