Metadata-Version: 2.1
Name: simplemachinesforum
Version: 0.4.5
Summary: Python request API to simplemachinesforum
Home-page: https://github.com/oliver-zehentleitner/python-simplemachinesforum
Author: Oliver Zehentleitner
License: MIT License
Project-URL: Wiki, https://github.com/oliver-zehentleitner/python-simplemachinesforum/wiki
Project-URL: Documentation, https://oliver-zehentleitner.github.io/python-simplemachinesforum
Project-URL: Author, https://about.me/oliver-zehentleitner/
Project-URL: Changes, https://github.com/oliver-zehentleitner/python-simplemachinesforum/blob/master/CHANGELOG.md
Project-URL: Issue Tracker, https://github.com/oliver-zehentleitner/python-simplemachinesforum/issues
Project-URL: Chat, https://gitter.im/python-simplemachinesforum/community
Project-URL: Get Support, https://www.lucit.tech/get-support.html
Keywords: simple machines forum,python,new post,create post,simplemachinesforum,api
Classifier: Development Status :: 5 - Production/Stable
Classifier: License :: OSI Approved :: MIT License
Classifier: Intended Audience :: Developers
Classifier: Operating System :: OS Independent
Classifier: Programming Language :: Python :: 3
Classifier: Topic :: Software Development :: Libraries :: Python Modules
License-File: LICENSE
Requires-Dist: requests
Requires-Dist: beautifulsoup4
